{"pk":122076,"titreFr":"Madam Butterfly","titreVo":"Húdié fūrén","titreNx":"蝴蝶夫人","realisateurs":"Tsai Ming-liang","annee":2008,"pays":"France-Taïwan","duree":"36:00","version":"VOSTA avec sous-titres français en option","isCC":true,"blockDefaultCC":true,"en":"Film with English subtitles","interpretation":"Pearly Chua","synopsis":"","restauration":"<p><em>Madame Butterfly</em> fait partie de la collection «&nbsp;Twenty Puccini&nbsp;» lancée dans le cadre de la commémoration du 120<sup>e</sup> anniversaire du compositeur à Lucques, sa ville natale. Remerciements à Antoine Barraud et Vincent Wang.</p>","comment":"","vimeo":"514281978","isCatFilm":false,"status":2,"datePublished":"2021-02-24","dateUnpublished":"2021-03-23","isPick":true,"isArchived":false,"collection":"Tout-monde","slug":"122076-madam-butterfly-tsai-ming-liang-2008","thumb":"https://www.cinematheque.fr/catalogues/restaurations-tirages-images/images/film/533x400/122076-1.jpg"}